README.md
setup.py
bayserver_docker_maccaferri/__init__.py
bayserver_docker_maccaferri/maccaferri_docker.py
bayserver_docker_maccaferri/maccaferri_train.py
bayserver_docker_maccaferri.egg-info/PKG-INFO
bayserver_docker_maccaferri.egg-info/SOURCES.txt
bayserver_docker_maccaferri.egg-info/dependency_links.txt
bayserver_docker_maccaferri.egg-info/requires.txt
bayserver_docker_maccaferri.egg-info/top_level.txt